Metadata-Version: 2.1
Name: hpyc-core
Version: 1.0.0
Summary: 这是一个基于python的高拓展性计算器
Home-page: https://github.com/HowieHz/hpyculator
Author: HowieHz
License: UNKNOWN
Project-URL: Bug Reports, https://github.com/HowieHz/hpyculator/issues
Platform: UNKNOWN
Classifier: License :: OSI Approved :: GNU Affero General Public License v3 or later (AGPLv3+)
Classifier: Operating System :: OS Independent
Classifier: Programming Language :: Python :: 3.10
